[
  {
    "source": "TennisApi",
    "odds_source": "TennisApi",
    "bookmaker": "TennisApi",
    "match_id": 16564419,
    "event_id": 16564419,
    "player1": "Titouan Droguet",
    "player2": "Camilo Ugo Carabelli",
    "home_team": "Titouan Droguet",
    "away_team": "Camilo Ugo Carabelli",
    "home_odds": 2.0,
    "away_odds": 1.8,
    "p1_odds": 2.0,
    "p2_odds": 1.8,
    "odds_player1": 2.0,
    "odds_player2": 1.8,
    "odds": 2.0,
    "odds1": 2.0,
    "odds2": 1.8,
    "price1": 2.0,
    "price2": 1.8,
    "raw": {
      "home": {
        "fractionalValue": "1/1",
        "expected": 50,
        "actual": 47,
        "id": 23201769
      },
      "away": {
        "fractionalValue": "4/5",
        "expected": 56,
        "actual": 83,
        "id": 23201770
      }
    }
  },
  {
    "source": "TennisApi",
    "odds_source": "TennisApi",
    "bookmaker": "TennisApi",
    "match_id": 16571680,
    "event_id": 16571680,
    "player1": "Henrique Rocha",
    "player2": "Pedro Martinez",
    "home_team": "Henrique Rocha",
    "away_team": "Pedro Martinez",
    "home_odds": 1.8,
    "away_odds": 2.0,
    "p1_odds": 1.8,
    "p2_odds": 2.0,
    "odds_player1": 1.8,
    "odds_player2": 2.0,
    "odds": 1.8,
    "odds1": 1.8,
    "odds2": 2.0,
    "price1": 1.8,
    "price2": 2.0,
    "raw": {
      "home": {
        "fractionalValue": "4/5",
        "expected": 56,
        "actual": 55,
        "id": 23228080
      },
      "away": {
        "fractionalValue": "1/1",
        "expected": 50,
        "actual": 44,
        "id": 23228081
      }
    }
  },
  {
    "source": "TennisApi",
    "odds_source": "TennisApi",
    "bookmaker": "TennisApi",
    "match_id": 16571629,
    "event_id": 16571629,
    "player1": "Gonzalo Bueno",
    "player2": "Tiago Pereira",
    "home_team": "Gonzalo Bueno",
    "away_team": "Tiago Pereira",
    "home_odds": 1.3,
    "away_odds": 3.5,
    "p1_odds": 1.3,
    "p2_odds": 3.5,
    "odds_player1": 1.3,
    "odds_player2": 3.5,
    "odds": 1.3,
    "odds1": 1.3,
    "odds2": 3.5,
    "price1": 1.3,
    "price2": 3.5,
    "raw": {
      "home": {
        "fractionalValue": "3/10",
        "expected": 77,
        "actual": 87,
        "id": 23229321
      },
      "away": {
        "fractionalValue": "5/2",
        "expected": 29,
        "actual": 32,
        "id": 23229322
      }
    }
  },
  {
    "source": "TennisApi",
    "odds_source": "TennisApi",
    "bookmaker": "TennisApi",
    "match_id": 16564423,
    "event_id": 16564423,
    "player1": "Jan Choinski",
    "player2": "Jesper De Jong",
    "home_team": "Jan Choinski",
    "away_team": "Jesper De Jong",
    "home_odds": 2.2,
    "away_odds": 1.67,
    "p1_odds": 2.2,
    "p2_odds": 1.67,
    "odds_player1": 2.2,
    "odds_player2": 1.67,
    "odds": 2.2,
    "odds1": 2.2,
    "odds2": 1.67,
    "price1": 2.2,
    "price2": 1.67,
    "raw": {
      "home": {
        "fractionalValue": "6/5",
        "expected": 45,
        "actual": 61,
        "id": 23201799
      },
      "away": {
        "fractionalValue": "67/100",
        "expected": 60,
        "actual": 76,
        "id": 23201800
      }
    }
  },
  {
    "source": "TennisApi",
    "odds_source": "TennisApi",
    "bookmaker": "TennisApi",
    "match_id": 16564421,
    "event_id": 16564421,
    "player1": "Vilius Gaubas",
    "player2": "Pablo Carreño Busta",
    "home_team": "Vilius Gaubas",
    "away_team": "Pablo Carreño Busta",
    "home_odds": 3.2,
    "away_odds": 1.36,
    "p1_odds": 3.2,
    "p2_odds": 1.36,
    "odds_player1": 3.2,
    "odds_player2": 1.36,
    "odds": 3.2,
    "odds1": 3.2,
    "odds2": 1.36,
    "price1": 3.2,
    "price2": 1.36,
    "raw": {
      "home": {
        "fractionalValue": "11/5",
        "expected": 31,
        "actual": 57,
        "id": 23201791
      },
      "away": {
        "fractionalValue": "9/25",
        "expected": 73,
        "actual": 83,
        "id": 23201792
      }
    }
  },
  {
    "source": "TennisApi",
    "odds_source": "TennisApi",
    "bookmaker": "TennisApi",
    "match_id": 16571628,
    "event_id": 16571628,
    "player1": "Daniel Merida",
    "player2": "Taro Daniel",
    "home_team": "Daniel Merida",
    "away_team": "Taro Daniel",
    "home_odds": 1.44,
    "away_odds": 2.75,
    "p1_odds": 1.44,
    "p2_odds": 2.75,
    "odds_player1": 1.44,
    "odds_player2": 2.75,
    "odds": 1.44,
    "odds1": 1.44,
    "odds2": 2.75,
    "price1": 1.44,
    "price2": 2.75,
    "raw": {
      "home": {
        "fractionalValue": "11/25",
        "expected": 69,
        "actual": 72,
        "id": 23229189
      },
      "away": {
        "fractionalValue": "7/4",
        "expected": 36,
        "actual": 36,
        "id": 23229190
      }
    }
  },
  {
    "source": "TennisApi",
    "odds_source": "TennisApi",
    "bookmaker": "TennisApi",
    "match_id": 16564412,
    "event_id": 16564412,
    "player1": "Hugo Gaston",
    "player2": "Damir Džumhur",
    "home_team": "Hugo Gaston",
    "away_team": "Damir Džumhur",
    "home_odds": 1.91,
    "away_odds": 1.91,
    "p1_odds": 1.91,
    "p2_odds": 1.91,
    "odds_player1": 1.91,
    "odds_player2": 1.91,
    "odds": 1.91,
    "odds1": 1.91,
    "odds2": 1.91,
    "price1": 1.91,
    "price2": 1.91,
    "raw": {
      "home": {
        "fractionalValue": "91/100",
        "expected": 52,
        "actual": 45,
        "id": 23202646
      },
      "away": {
        "fractionalValue": "91/100",
        "expected": 52,
        "actual": 67,
        "id": 23202647
      }
    }
  },
  {
    "source": "TennisApi",
    "odds_source": "TennisApi",
    "bookmaker": "TennisApi",
    "match_id": 16579976,
    "event_id": 16579976,
    "player1": "Daniel Merida",
    "player2": "Kyrian Jacquet",
    "home_team": "Daniel Merida",
    "away_team": "Kyrian Jacquet",
    "home_odds": 1.4,
    "away_odds": 3.0,
    "p1_odds": 1.4,
    "p2_odds": 3.0,
    "odds_player1": 1.4,
    "odds_player2": 3.0,
    "odds": 1.4,
    "odds1": 1.4,
    "odds2": 3.0,
    "price1": 1.4,
    "price2": 3.0,
    "raw": {
      "home": {
        "fractionalValue": "2/5",
        "expected": 71,
        "actual": 78,
        "id": 23270377
      },
      "away": {
        "fractionalValue": "2/1",
        "expected": 33,
        "actual": 45,
        "id": 23277798
      }
    }
  },
  {
    "source": "TennisApi",
    "odds_source": "TennisApi",
    "bookmaker": "TennisApi",
    "match_id": 16564414,
    "event_id": 16564414,
    "player1": "Stan Wawrinka",
    "player2": "Roman Andres Burruchaga",
    "home_team": "Stan Wawrinka",
    "away_team": "Roman Andres Burruchaga",
    "home_odds": 2.75,
    "away_odds": 1.44,
    "p1_odds": 2.75,
    "p2_odds": 1.44,
    "odds_player1": 2.75,
    "odds_player2": 1.44,
    "odds": 2.75,
    "odds1": 2.75,
    "odds2": 1.44,
    "price1": 2.75,
    "price2": 1.44,
    "raw": {
      "home": {
        "fractionalValue": "7/4",
        "expected": 36,
        "actual": 50,
        "id": 23229037
      },
      "away": {
        "fractionalValue": "11/25",
        "expected": 69,
        "actual": 69,
        "id": 23229038
      }
    }
  },
  {
    "source": "TennisApi",
    "odds_source": "TennisApi",
    "bookmaker": "TennisApi",
    "match_id": 16564418,
    "event_id": 16564418,
    "player1": "Botic Van de Zandschulp",
    "player2": "Jaime Faria",
    "home_team": "Botic Van de Zandschulp",
    "away_team": "Jaime Faria",
    "home_odds": 2.2,
    "away_odds": 1.67,
    "p1_odds": 2.2,
    "p2_odds": 1.67,
    "odds_player1": 2.2,
    "odds_player2": 1.67,
    "odds": 2.2,
    "odds1": 2.2,
    "odds2": 1.67,
    "price1": 2.2,
    "price2": 1.67,
    "raw": {
      "home": {
        "fractionalValue": "6/5",
        "expected": 45,
        "actual": 50,
        "id": 23201783
      },
      "away": {
        "fractionalValue": "67/100",
        "expected": 60,
        "actual": 63,
        "id": 23201784
      }
    }
  },
  {
    "source": "TennisApi",
    "odds_source": "TennisApi",
    "bookmaker": "TennisApi",
    "match_id": 16515726,
    "event_id": 16515726,
    "player1": "Pedro Martinez",
    "player2": "Luciano Darderi",
    "home_team": "Pedro Martinez",
    "away_team": "Luciano Darderi",
    "home_odds": 4.0,
    "away_odds": 1.25,
    "p1_odds": 4.0,
    "p2_odds": 1.25,
    "odds_player1": 4.0,
    "odds_player2": 1.25,
    "odds": 4.0,
    "odds1": 4.0,
    "odds2": 1.25,
    "price1": 4.0,
    "price2": 1.25,
    "raw": {
      "home": {
        "fractionalValue": "3/1",
        "expected": 25,
        "actual": 18,
        "id": 23265587
      },
      "away": {
        "fractionalValue": "1/4",
        "expected": 80,
        "actual": 81,
        "id": 23265588
      }
    }
  },
  {
    "source": "TennisApi",
    "odds_source": "TennisApi",
    "bookmaker": "TennisApi",
    "match_id": 16571611,
    "event_id": 16571611,
    "player1": "Facundo Diaz Acosta",
    "player2": "Federico Cinà",
    "home_team": "Facundo Diaz Acosta",
    "away_team": "Federico Cinà",
    "home_odds": 1.57,
    "away_odds": 2.38,
    "p1_odds": 1.57,
    "p2_odds": 2.38,
    "odds_player1": 1.57,
    "odds_player2": 2.38,
    "odds": 1.57,
    "odds1": 1.57,
    "odds2": 2.38,
    "price1": 1.57,
    "price2": 2.38,
    "raw": {
      "home": {
        "fractionalValue": "57/100",
        "expected": 64,
        "actual": 56,
        "id": 23228117
      },
      "away": {
        "fractionalValue": "69/50",
        "expected": 42,
        "actual": 27,
        "id": 23228118
      }
    }
  },
  {
    "source": "TennisApi",
    "odds_source": "TennisApi",
    "bookmaker": "TennisApi",
    "match_id": 16571610,
    "event_id": 16571610,
    "player1": "Joel Schwaerzler",
    "player2": "Jurij Rodionov",
    "home_team": "Joel Schwaerzler",
    "away_team": "Jurij Rodionov",
    "home_odds": 2.38,
    "away_odds": 1.57,
    "p1_odds": 2.38,
    "p2_odds": 1.57,
    "odds_player1": 2.38,
    "odds_player2": 1.57,
    "odds": 2.38,
    "odds1": 2.38,
    "odds2": 1.57,
    "price1": 2.38,
    "price2": 1.57,
    "raw": {
      "home": {
        "fractionalValue": "69/50",
        "expected": 42,
        "actual": 46,
        "id": 23228115
      },
      "away": {
        "fractionalValue": "57/100",
        "expected": 64,
        "actual": 67,
        "id": 23228116
      }
    }
  },
  {
    "source": "TennisApi",
    "odds_source": "TennisApi",
    "bookmaker": "TennisApi",
    "match_id": 16562591,
    "event_id": 16562591,
    "player1": "Vit Kopřiva",
    "player2": "Ignacio Buse",
    "home_team": "Vit Kopřiva",
    "away_team": "Ignacio Buse",
    "home_odds": 2.5,
    "away_odds": 1.53,
    "p1_odds": 2.5,
    "p2_odds": 1.53,
    "odds_player1": 2.5,
    "odds_player2": 1.53,
    "odds": 2.5,
    "odds1": 2.5,
    "odds2": 1.53,
    "price1": 2.5,
    "price2": 1.53,
    "raw": {
      "home": {
        "fractionalValue": "3/2",
        "expected": 40,
        "actual": 47,
        "id": 23197608
      },
      "away": {
        "fractionalValue": "53/100",
        "expected": 65,
        "actual": 71,
        "id": 23197609
      }
    }
  },
  {
    "source": "TennisApi",
    "odds_source": "TennisApi",
    "bookmaker": "TennisApi",
    "match_id": 16562587,
    "event_id": 16562587,
    "player1": "Jan-Lennard Struff",
    "player2": "Aleksandr Shevchenko",
    "home_team": "Jan-Lennard Struff",
    "away_team": "Aleksandr Shevchenko",
    "home_odds": 1.67,
    "away_odds": 2.2,
    "p1_odds": 1.67,
    "p2_odds": 2.2,
    "odds_player1": 1.67,
    "odds_player2": 2.2,
    "odds": 1.67,
    "odds1": 1.67,
    "odds2": 2.2,
    "price1": 1.67,
    "price2": 2.2,
    "raw": {
      "home": {
        "fractionalValue": "67/100",
        "expected": 60,
        "actual": 21,
        "id": 23197568
      },
      "away": {
        "fractionalValue": "6/5",
        "expected": 45,
        "actual": 40,
        "id": 23197569
      }
    }
  },
  {
    "source": "TennisApi",
    "odds_source": "TennisApi",
    "bookmaker": "TennisApi",
    "match_id": 16562590,
    "event_id": 16562590,
    "player1": "Juan Manuel Cerundolo",
    "player2": "Marco Trungelliti",
    "home_team": "Juan Manuel Cerundolo",
    "away_team": "Marco Trungelliti",
    "home_odds": 1.33,
    "away_odds": 3.4,
    "p1_odds": 1.33,
    "p2_odds": 3.4,
    "odds_player1": 1.33,
    "odds_player2": 3.4,
    "odds": 1.33,
    "odds1": 1.33,
    "odds2": 3.4,
    "price1": 1.33,
    "price2": 3.4,
    "raw": {
      "home": {
        "fractionalValue": "33/100",
        "expected": 75,
        "actual": 80,
        "id": 23197544
      },
      "away": {
        "fractionalValue": "12/5",
        "expected": 29,
        "actual": 21,
        "id": 23197545
      }
    }
  },
  {
    "source": "TennisApi",
    "odds_source": "TennisApi",
    "bookmaker": "TennisApi",
    "match_id": 16562588,
    "event_id": 16562588,
    "player1": "Sebastián Báez",
    "player2": "Miomir Kecmanović",
    "home_team": "Sebastián Báez",
    "away_team": "Miomir Kecmanović",
    "home_odds": 2.2,
    "away_odds": 1.67,
    "p1_odds": 2.2,
    "p2_odds": 1.67,
    "odds_player1": 2.2,
    "odds_player2": 1.67,
    "odds": 2.2,
    "odds1": 2.2,
    "odds2": 1.67,
    "price1": 2.2,
    "price2": 1.67,
    "raw": {
      "home": {
        "fractionalValue": "6/5",
        "expected": 45,
        "actual": 42,
        "id": 23197534
      },
      "away": {
        "fractionalValue": "67/100",
        "expected": 60,
        "actual": 56,
        "id": 23197535
      }
    }
  },
  {
    "source": "TennisApi",
    "odds_source": "TennisApi",
    "bookmaker": "TennisApi",
    "match_id": 16571617,
    "event_id": 16571617,
    "player1": "Laslo Djere",
    "player2": "Quentin Halys",
    "home_team": "Laslo Djere",
    "away_team": "Quentin Halys",
    "home_odds": 1.57,
    "away_odds": 2.38,
    "p1_odds": 1.57,
    "p2_odds": 2.38,
    "odds_player1": 1.57,
    "odds_player2": 2.38,
    "odds": 1.57,
    "odds1": 1.57,
    "odds2": 2.38,
    "price1": 1.57,
    "price2": 2.38,
    "raw": {
      "home": {
        "fractionalValue": "57/100",
        "expected": 64,
        "actual": 75,
        "id": 23230846
      },
      "away": {
        "fractionalValue": "69/50",
        "expected": 42,
        "actual": 50,
        "id": 23230847
      }
    }
  },
  {
    "source": "TennisApi",
    "odds_source": "TennisApi",
    "bookmaker": "TennisApi",
    "match_id": 16571618,
    "event_id": 16571618,
    "player1": "Adolfo Daniel Vallejo",
    "player2": "Kilian Feldbausch",
    "home_team": "Adolfo Daniel Vallejo",
    "away_team": "Kilian Feldbausch",
    "home_odds": 1.53,
    "away_odds": 2.5,
    "p1_odds": 1.53,
    "p2_odds": 2.5,
    "odds_player1": 1.53,
    "odds_player2": 2.5,
    "odds": 1.53,
    "odds1": 1.53,
    "odds2": 2.5,
    "price1": 1.53,
    "price2": 2.5,
    "raw": {
      "home": {
        "fractionalValue": "53/100",
        "expected": 65,
        "actual": 70,
        "id": 23229257
      },
      "away": {
        "fractionalValue": "3/2",
        "expected": 40,
        "actual": 44,
        "id": 23229258
      }
    }
  },
  {
    "source": "TennisApi",
    "odds_source": "TennisApi",
    "bookmaker": "TennisApi",
    "match_id": 16562593,
    "event_id": 16562593,
    "player1": "Alex Molčan",
    "player2": "Sebastian Ofner",
    "home_team": "Alex Molčan",
    "away_team": "Sebastian Ofner",
    "home_odds": 1.67,
    "away_odds": 2.2,
    "p1_odds": 1.67,
    "p2_odds": 2.2,
    "odds_player1": 1.67,
    "odds_player2": 2.2,
    "odds": 1.67,
    "odds1": 1.67,
    "odds2": 2.2,
    "price1": 1.67,
    "price2": 2.2,
    "raw": {
      "home": {
        "fractionalValue": "67/100",
        "expected": 60,
        "actual": 69,
        "id": 23197628
      },
      "away": {
        "fractionalValue": "6/5",
        "expected": 45,
        "actual": 55,
        "id": 23197629
      }
    }
  },
  {
    "source": "TennisApi",
    "odds_source": "TennisApi",
    "bookmaker": "TennisApi",
    "match_id": 16562592,
    "event_id": 16562592,
    "player1": "Daniel Altmaier",
    "player2": "Raphael Collignon",
    "home_team": "Daniel Altmaier",
    "away_team": "Raphael Collignon",
    "home_odds": 2.38,
    "away_odds": 1.57,
    "p1_odds": 2.38,
    "p2_odds": 1.57,
    "odds_player1": 2.38,
    "odds_player2": 1.57,
    "odds": 2.38,
    "odds1": 2.38,
    "odds2": 1.57,
    "price1": 2.38,
    "price2": 1.57,
    "raw": {
      "home": {
        "fractionalValue": "69/50",
        "expected": 42,
        "actual": 35,
        "id": 23229197
      },
      "away": {
        "fractionalValue": "57/100",
        "expected": 64,
        "actual": 82,
        "id": 23229198
      }
    }
  },
  {
    "source": "TennisApi",
    "odds_source": "TennisApi",
    "bookmaker": "TennisApi",
    "match_id": 16515759,
    "event_id": 16515759,
    "player1": "Alexander Bublik",
    "player2": "Facundo Diaz Acosta",
    "home_team": "Alexander Bublik",
    "away_team": "Facundo Diaz Acosta",
    "home_odds": 1.62,
    "away_odds": 2.3,
    "p1_odds": 1.62,
    "p2_odds": 2.3,
    "odds_player1": 1.62,
    "odds_player2": 2.3,
    "odds": 1.62,
    "odds1": 1.62,
    "odds2": 2.3,
    "price1": 1.62,
    "price2": 2.3,
    "raw": {
      "home": {
        "fractionalValue": "31/50",
        "expected": 62,
        "actual": 72,
        "id": 23260532
      },
      "away": {
        "fractionalValue": "13/10",
        "expected": 43,
        "actual": 10,
        "id": 23260533
      }
    }
  },
  {
    "source": "TennisApi",
    "odds_source": "TennisApi",
    "bookmaker": "TennisApi",
    "match_id": 16515768,
    "event_id": 16515768,
    "player1": "Tomas Martin Etcheverry",
    "player2": "Jurij Rodionov",
    "home_team": "Tomas Martin Etcheverry",
    "away_team": "Jurij Rodionov",
    "home_odds": 1.53,
    "away_odds": 2.5,
    "p1_odds": 1.53,
    "p2_odds": 2.5,
    "odds_player1": 1.53,
    "odds_player2": 2.5,
    "odds": 1.53,
    "odds1": 1.53,
    "odds2": 2.5,
    "price1": 1.53,
    "price2": 2.5,
    "raw": {
      "home": {
        "fractionalValue": "53/100",
        "expected": 65,
        "actual": 68,
        "id": 23260479
      },
      "away": {
        "fractionalValue": "3/2",
        "expected": 40,
        "actual": 13,
        "id": 23260480
      }
    }
  },
  {
    "source": "TennisApi",
    "odds_source": "TennisApi",
    "bookmaker": "TennisApi",
    "match_id": 16562568,
    "event_id": 16562568,
    "player1": "Frantzen C / Haase R",
    "player2": "Nouza P / Oberleitner N",
    "home_team": "Frantzen C / Haase R",
    "away_team": "Nouza P / Oberleitner N",
    "home_odds": 2.5,
    "away_odds": 1.5,
    "p1_odds": 2.5,
    "p2_odds": 1.5,
    "odds_player1": 2.5,
    "odds_player2": 1.5,
    "odds": 2.5,
    "odds1": 2.5,
    "odds2": 1.5,
    "price1": 2.5,
    "price2": 1.5,
    "raw": {
      "home": {
        "fractionalValue": "3/2",
        "expected": 40,
        "actual": 60,
        "id": 23197502
      },
      "away": {
        "fractionalValue": "1/2",
        "expected": 67,
        "actual": 80,
        "id": 23267036
      }
    }
  },
  {
    "source": "TennisApi",
    "odds_source": "TennisApi",
    "bookmaker": "TennisApi",
    "match_id": 16570807,
    "event_id": 16570807,
    "player1": "Kaitlin Quevedo",
    "player2": "Anhelina Kalinina",
    "home_team": "Kaitlin Quevedo",
    "away_team": "Anhelina Kalinina",
    "home_odds": 2.75,
    "away_odds": 1.44,
    "p1_odds": 2.75,
    "p2_odds": 1.44,
    "odds_player1": 2.75,
    "odds_player2": 1.44,
    "odds": 2.75,
    "odds1": 2.75,
    "odds2": 1.44,
    "price1": 2.75,
    "price2": 1.44,
    "raw": {
      "home": {
        "fractionalValue": "7/4",
        "expected": 36,
        "actual": 29,
        "id": 23224082
      },
      "away": {
        "fractionalValue": "11/25",
        "expected": 69,
        "actual": 61,
        "id": 23224083
      }
    }
  },
  {
    "source": "TennisApi",
    "odds_source": "TennisApi",
    "bookmaker": "TennisApi",
    "match_id": 16570816,
    "event_id": 16570816,
    "player1": "Anna Bondar",
    "player2": "Moyuka Uchijima",
    "home_team": "Anna Bondar",
    "away_team": "Moyuka Uchijima",
    "home_odds": 1.33,
    "away_odds": 3.4,
    "p1_odds": 1.33,
    "p2_odds": 3.4,
    "odds_player1": 1.33,
    "odds_player2": 3.4,
    "odds": 1.33,
    "odds1": 1.33,
    "odds2": 3.4,
    "price1": 1.33,
    "price2": 3.4,
    "raw": {
      "home": {
        "fractionalValue": "33/100",
        "expected": 75,
        "actual": 85,
        "id": 23224030
      },
      "away": {
        "fractionalValue": "12/5",
        "expected": 29,
        "actual": 42,
        "id": 23224031
      }
    }
  },
  {
    "source": "TennisApi",
    "odds_source": "TennisApi",
    "bookmaker": "TennisApi",
    "match_id": 16579638,
    "event_id": 16579638,
    "player1": "Elena Pridankina",
    "player2": "Panna Udvardy",
    "home_team": "Elena Pridankina",
    "away_team": "Panna Udvardy",
    "home_odds": 2.1,
    "away_odds": 1.73,
    "p1_odds": 2.1,
    "p2_odds": 1.73,
    "odds_player1": 2.1,
    "odds_player2": 1.73,
    "odds": 2.1,
    "odds1": 2.1,
    "odds2": 1.73,
    "price1": 2.1,
    "price2": 1.73,
    "raw": {
      "home": {
        "fractionalValue": "11/10",
        "expected": 48,
        "actual": 38,
        "id": 23260509
      },
      "away": {
        "fractionalValue": "73/100",
        "expected": 58,
        "actual": 69,
        "id": 23260510
      }
    }
  },
  {
    "source": "TennisApi",
    "odds_source": "TennisApi",
    "bookmaker": "TennisApi",
    "match_id": 16570813,
    "event_id": 16570813,
    "player1": "Darja Semenistaja",
    "player2": "Sinja Kraus",
    "home_team": "Darja Semenistaja",
    "away_team": "Sinja Kraus",
    "home_odds": 3.75,
    "away_odds": 1.28,
    "p1_odds": 3.75,
    "p2_odds": 1.28,
    "odds_player1": 3.75,
    "odds_player2": 1.28,
    "odds": 3.75,
    "odds1": 3.75,
    "odds2": 1.28,
    "price1": 3.75,
    "price2": 1.28,
    "raw": {
      "home": {
        "fractionalValue": "11/4",
        "expected": 27,
        "actual": 33,
        "id": 23223974
      },
      "away": {
        "fractionalValue": "7/25",
        "expected": 78,
        "actual": 78,
        "id": 23223975
      }
    }
  },
  {
    "source": "TennisApi",
    "odds_source": "TennisApi",
    "bookmaker": "TennisApi",
    "match_id": 16570817,
    "event_id": 16570817,
    "player1": "Leyre Romero Gormaz",
    "player2": "Veronika Erjavec",
    "home_team": "Leyre Romero Gormaz",
    "away_team": "Veronika Erjavec",
    "home_odds": 2.1,
    "away_odds": 1.73,
    "p1_odds": 2.1,
    "p2_odds": 1.73,
    "odds_player1": 2.1,
    "odds_player2": 1.73,
    "odds": 2.1,
    "odds1": 2.1,
    "odds2": 1.73,
    "price1": 2.1,
    "price2": 1.73,
    "raw": {
      "home": {
        "fractionalValue": "11/10",
        "expected": 48,
        "actual": 43,
        "id": 23222880
      },
      "away": {
        "fractionalValue": "73/100",
        "expected": 58,
        "actual": 36,
        "id": 23222881
      }
    }
  },
  {
    "source": "TennisApi",
    "odds_source": "TennisApi",
    "bookmaker": "TennisApi",
    "match_id": 16570815,
    "event_id": 16570815,
    "player1": "Valentina Steiner",
    "player2": "Noma Noha Akugue",
    "home_team": "Valentina Steiner",
    "away_team": "Noma Noha Akugue",
    "home_odds": 4.0,
    "away_odds": 1.25,
    "p1_odds": 4.0,
    "p2_odds": 1.25,
    "odds_player1": 4.0,
    "odds_player2": 1.25,
    "odds": 4.0,
    "odds1": 4.0,
    "odds2": 1.25,
    "price1": 4.0,
    "price2": 1.25,
    "raw": {
      "home": {
        "fractionalValue": "3/1",
        "expected": 25,
        "actual": 33,
        "id": 23224012
      },
      "away": {
        "fractionalValue": "1/4",
        "expected": 80,
        "actual": 81,
        "id": 23224013
      }
    }
  },
  {
    "source": "TennisApi",
    "odds_source": "TennisApi",
    "bookmaker": "TennisApi",
    "match_id": 16579637,
    "event_id": 16579637,
    "player1": "Maria Carle",
    "player2": "Jule Niemeier",
    "home_team": "Maria Carle",
    "away_team": "Jule Niemeier",
    "home_odds": 1.44,
    "away_odds": 2.75,
    "p1_odds": 1.44,
    "p2_odds": 2.75,
    "odds_player1": 1.44,
    "odds_player2": 2.75,
    "odds": 1.44,
    "odds1": 1.44,
    "odds2": 2.75,
    "price1": 1.44,
    "price2": 2.75,
    "raw": {
      "home": {
        "fractionalValue": "11/25",
        "expected": 69,
        "actual": 63,
        "id": 23260502
      },
      "away": {
        "fractionalValue": "7/4",
        "expected": 36,
        "actual": 57,
        "id": 23260503
      }
    }
  },
  {
    "source": "TennisApi",
    "odds_source": "TennisApi",
    "bookmaker": "TennisApi",
    "match_id": 16570814,
    "event_id": 16570814,
    "player1": "Sara Sorribes Tormo",
    "player2": "Alina Charaeva",
    "home_team": "Sara Sorribes Tormo",
    "away_team": "Alina Charaeva",
    "home_odds": 2.1,
    "away_odds": 1.73,
    "p1_odds": 2.1,
    "p2_odds": 1.73,
    "odds_player1": 2.1,
    "odds_player2": 1.73,
    "odds": 2.1,
    "odds1": 2.1,
    "odds2": 1.73,
    "price1": 2.1,
    "price2": 1.73,
    "raw": {
      "home": {
        "fractionalValue": "11/10",
        "expected": 48,
        "actual": 30,
        "id": 23223993
      },
      "away": {
        "fractionalValue": "73/100",
        "expected": 58,
        "actual": 67,
        "id": 23223994
      }
    }
  },
  {
    "source": "TennisApi",
    "odds_source": "TennisApi",
    "bookmaker": "TennisApi",
    "match_id": 16579640,
    "event_id": 16579640,
    "player1": "Arantxa Rus",
    "player2": "Elina Avanesyan",
    "home_team": "Arantxa Rus",
    "away_team": "Elina Avanesyan",
    "home_odds": 3.2,
    "away_odds": 1.36,
    "p1_odds": 3.2,
    "p2_odds": 1.36,
    "odds_player1": 3.2,
    "odds_player2": 1.36,
    "odds": 3.2,
    "odds1": 3.2,
    "odds2": 1.36,
    "price1": 3.2,
    "price2": 1.36,
    "raw": {
      "home": {
        "fractionalValue": "11/5",
        "expected": 31,
        "actual": 10,
        "id": 23260475
      },
      "away": {
        "fractionalValue": "9/25",
        "expected": 73,
        "actual": 75,
        "id": 23260476
      }
    }
  },
  {
    "source": "TennisApi",
    "odds_source": "TennisApi",
    "bookmaker": "TennisApi",
    "match_id": 16570809,
    "event_id": 16570809,
    "player1": "Tamara Korpatsch",
    "player2": "Victoria Jimenez Kasintseva",
    "home_team": "Tamara Korpatsch",
    "away_team": "Victoria Jimenez Kasintseva",
    "home_odds": 1.4,
    "away_odds": 3.0,
    "p1_odds": 1.4,
    "p2_odds": 3.0,
    "odds_player1": 1.4,
    "odds_player2": 3.0,
    "odds": 1.4,
    "odds1": 1.4,
    "odds2": 3.0,
    "price1": 1.4,
    "price2": 3.0,
    "raw": {
      "home": {
        "fractionalValue": "2/5",
        "expected": 71,
        "actual": 75,
        "id": 23224118
      },
      "away": {
        "fractionalValue": "2/1",
        "expected": 33,
        "actual": 30,
        "id": 23224119
      }
    }
  },
  {
    "source": "TennisApi",
    "odds_source": "TennisApi",
    "bookmaker": "TennisApi",
    "match_id": 16570818,
    "event_id": 16570818,
    "player1": "Oleksandra Oliynykova",
    "player2": "Nastasja Schunk",
    "home_team": "Oleksandra Oliynykova",
    "away_team": "Nastasja Schunk",
    "home_odds": 1.33,
    "away_odds": 3.4,
    "p1_odds": 1.33,
    "p2_odds": 3.4,
    "odds_player1": 1.33,
    "odds_player2": 3.4,
    "odds": 1.33,
    "odds1": 1.33,
    "odds2": 3.4,
    "price1": 1.33,
    "price2": 3.4,
    "raw": {
      "home": {
        "fractionalValue": "33/100",
        "expected": 75,
        "actual": 81,
        "id": 23222886
      },
      "away": {
        "fractionalValue": "12/5",
        "expected": 29,
        "actual": 17,
        "id": 23222887
      }
    }
  },
  {
    "source": "TennisApi",
    "odds_source": "TennisApi",
    "bookmaker": "TennisApi",
    "match_id": 16570811,
    "event_id": 16570811,
    "player1": "Tessa Johanna Brockmann",
    "player2": "Elsa Jacquemot",
    "home_team": "Tessa Johanna Brockmann",
    "away_team": "Elsa Jacquemot",
    "home_odds": 2.63,
    "away_odds": 1.5,
    "p1_odds": 2.63,
    "p2_odds": 1.5,
    "odds_player1": 2.63,
    "odds_player2": 1.5,
    "odds": 2.63,
    "odds1": 2.63,
    "odds2": 1.5,
    "price1": 2.63,
    "price2": 1.5,
    "raw": {
      "home": {
        "fractionalValue": "163/100",
        "expected": 38,
        "actual": 43,
        "id": 23223956
      },
      "away": {
        "fractionalValue": "1/2",
        "expected": 67,
        "actual": 53,
        "id": 23223957
      }
    }
  },
  {
    "source": "TennisApi",
    "odds_source": "TennisApi",
    "bookmaker": "TennisApi",
    "match_id": 16570810,
    "event_id": 16570810,
    "player1": "Katarzyna Kawa",
    "player2": "Paula Badosa",
    "home_team": "Katarzyna Kawa",
    "away_team": "Paula Badosa",
    "home_odds": 2.38,
    "away_odds": 1.57,
    "p1_odds": 2.38,
    "p2_odds": 1.57,
    "odds_player1": 2.38,
    "odds_player2": 1.57,
    "odds": 2.38,
    "odds1": 2.38,
    "odds2": 1.57,
    "price1": 2.38,
    "price2": 1.57,
    "raw": {
      "home": {
        "fractionalValue": "69/50",
        "expected": 42,
        "actual": 22,
        "id": 23223934
      },
      "away": {
        "fractionalValue": "57/100",
        "expected": 64,
        "actual": 60,
        "id": 23223935
      }
    }
  },
  {
    "source": "TennisApi",
    "odds_source": "TennisApi",
    "bookmaker": "TennisApi",
    "match_id": 16570812,
    "event_id": 16570812,
    "player1": "Simona Waltert",
    "player2": "Mayar Sherif",
    "home_team": "Simona Waltert",
    "away_team": "Mayar Sherif",
    "home_odds": 2.1,
    "away_odds": 1.73,
    "p1_odds": 2.1,
    "p2_odds": 1.73,
    "odds_player1": 2.1,
    "odds_player2": 1.73,
    "odds": 2.1,
    "odds1": 2.1,
    "odds2": 1.73,
    "price1": 2.1,
    "price2": 1.73,
    "raw": {
      "home": {
        "fractionalValue": "11/10",
        "expected": 48,
        "actual": 59,
        "id": 23224228
      },
      "away": {
        "fractionalValue": "73/100",
        "expected": 58,
        "actual": 50,
        "id": 23224229
      }
    }
  },
  {
    "source": "TennisApi",
    "odds_source": "TennisApi",
    "bookmaker": "TennisApi",
    "match_id": 16571604,
    "event_id": 16571604,
    "player1": "Ayla Aksu",
    "player2": "Sofia Costoulas",
    "home_team": "Ayla Aksu",
    "away_team": "Sofia Costoulas",
    "home_odds": 2.75,
    "away_odds": 1.44,
    "p1_odds": 2.75,
    "p2_odds": 1.44,
    "odds_player1": 2.75,
    "odds_player2": 1.44,
    "odds": 2.75,
    "odds1": 2.75,
    "odds2": 1.44,
    "price1": 2.75,
    "price2": 1.44,
    "raw": {
      "home": {
        "fractionalValue": "7/4",
        "expected": 36,
        "actual": 36,
        "id": 23225417
      },
      "away": {
        "fractionalValue": "11/25",
        "expected": 69,
        "actual": 76,
        "id": 23225418
      }
    }
  },
  {
    "source": "TennisApi",
    "odds_source": "TennisApi",
    "bookmaker": "TennisApi",
    "match_id": 16571600,
    "event_id": 16571600,
    "player1": "Antonia Ružić",
    "player2": "Dominika Salkova",
    "home_team": "Antonia Ružić",
    "away_team": "Dominika Salkova",
    "home_odds": 1.8,
    "away_odds": 2.0,
    "p1_odds": 1.8,
    "p2_odds": 2.0,
    "odds_player1": 1.8,
    "odds_player2": 2.0,
    "odds": 1.8,
    "odds1": 1.8,
    "odds2": 2.0,
    "price1": 1.8,
    "price2": 2.0,
    "raw": {
      "home": {
        "fractionalValue": "4/5",
        "expected": 56,
        "actual": 52,
        "id": 23225407
      },
      "away": {
        "fractionalValue": "1/1",
        "expected": 50,
        "actual": 44,
        "id": 23225408
      }
    }
  },
  {
    "source": "TennisApi",
    "odds_source": "TennisApi",
    "bookmaker": "TennisApi",
    "match_id": 16571598,
    "event_id": 16571598,
    "player1": "Diane Parry",
    "player2": "Mai Hontama",
    "home_team": "Diane Parry",
    "away_team": "Mai Hontama",
    "home_odds": 1.53,
    "away_odds": 2.5,
    "p1_odds": 1.53,
    "p2_odds": 2.5,
    "odds_player1": 1.53,
    "odds_player2": 2.5,
    "odds": 1.53,
    "odds1": 1.53,
    "odds2": 2.5,
    "price1": 1.53,
    "price2": 2.5,
    "raw": {
      "home": {
        "fractionalValue": "53/100",
        "expected": 65,
        "actual": 53,
        "id": 23226084
      },
      "away": {
        "fractionalValue": "3/2",
        "expected": 40,
        "actual": 40,
        "id": 23226085
      }
    }
  },
  {
    "source": "TennisApi",
    "odds_source": "TennisApi",
    "bookmaker": "TennisApi",
    "match_id": 16564865,
    "event_id": 16564865,
    "player1": "Eva Lys",
    "player2": "Tereza Valentová",
    "home_team": "Eva Lys",
    "away_team": "Tereza Valentová",
    "home_odds": 3.0,
    "away_odds": 1.4,
    "p1_odds": 3.0,
    "p2_odds": 1.4,
    "odds_player1": 3.0,
    "odds_player2": 1.4,
    "odds": 3.0,
    "odds1": 3.0,
    "odds2": 1.4,
    "price1": 3.0,
    "price2": 1.4,
    "raw": {
      "home": {
        "fractionalValue": "2/1",
        "expected": 33,
        "actual": 25,
        "id": 23202662
      },
      "away": {
        "fractionalValue": "2/5",
        "expected": 71,
        "actual": 82,
        "id": 23202663
      }
    }
  },
  {
    "source": "TennisApi",
    "odds_source": "TennisApi",
    "bookmaker": "TennisApi",
    "match_id": 16564860,
    "event_id": 16564860,
    "player1": "Maria Timofeeva",
    "player2": "Aliaksandra Sasnovich",
    "home_team": "Maria Timofeeva",
    "away_team": "Aliaksandra Sasnovich",
    "home_odds": 2.1,
    "away_odds": 1.73,
    "p1_odds": 2.1,
    "p2_odds": 1.73,
    "odds_player1": 2.1,
    "odds_player2": 1.73,
    "odds": 2.1,
    "odds1": 2.1,
    "odds2": 1.73,
    "price1": 2.1,
    "price2": 1.73,
    "raw": {
      "home": {
        "fractionalValue": "11/10",
        "expected": 48,
        "actual": 60,
        "id": 23202654
      },
      "away": {
        "fractionalValue": "73/100",
        "expected": 58,
        "actual": 64,
        "id": 23202655
      }
    }
  },
  {
    "source": "TennisApi",
    "odds_source": "TennisApi",
    "bookmaker": "TennisApi",
    "match_id": 16564864,
    "event_id": 16564864,
    "player1": "Nikola Bartunkova",
    "player2": "Yue Yuan",
    "home_team": "Nikola Bartunkova",
    "away_team": "Yue Yuan",
    "home_odds": 1.33,
    "away_odds": 3.4,
    "p1_odds": 1.33,
    "p2_odds": 3.4,
    "odds_player1": 1.33,
    "odds_player2": 3.4,
    "odds": 1.33,
    "odds1": 1.33,
    "odds2": 3.4,
    "price1": 1.33,
    "price2": 3.4,
    "raw": {
      "home": {
        "fractionalValue": "33/100",
        "expected": 75,
        "actual": 72,
        "id": 23202686
      },
      "away": {
        "fractionalValue": "12/5",
        "expected": 29,
        "actual": 14,
        "id": 23202687
      }
    }
  },
  {
    "source": "TennisApi",
    "odds_source": "TennisApi",
    "bookmaker": "TennisApi",
    "match_id": 16564866,
    "event_id": 16564866,
    "player1": "Laura Samson",
    "player2": "Maya Joint",
    "home_team": "Laura Samson",
    "away_team": "Maya Joint",
    "home_odds": 2.3,
    "away_odds": 1.62,
    "p1_odds": 2.3,
    "p2_odds": 1.62,
    "odds_player1": 2.3,
    "odds_player2": 1.62,
    "odds": 2.3,
    "odds1": 2.3,
    "odds2": 1.62,
    "price1": 2.3,
    "price2": 1.62,
    "raw": {
      "home": {
        "fractionalValue": "13/10",
        "expected": 43,
        "actual": 27,
        "id": 23202696
      },
      "away": {
        "fractionalValue": "31/50",
        "expected": 62,
        "actual": 63,
        "id": 23202697
      }
    }
  },
  {
    "source": "TennisApi",
    "odds_source": "TennisApi",
    "bookmaker": "TennisApi",
    "match_id": 16571599,
    "event_id": 16571599,
    "player1": "Xinyu Gao",
    "player2": "Lilli Tagger",
    "home_team": "Xinyu Gao",
    "away_team": "Lilli Tagger",
    "home_odds": 2.63,
    "away_odds": 1.5,
    "p1_odds": 2.63,
    "p2_odds": 1.5,
    "odds_player1": 2.63,
    "odds_player2": 1.5,
    "odds": 2.63,
    "odds1": 2.63,
    "odds2": 1.5,
    "price1": 2.63,
    "price2": 1.5,
    "raw": {
      "home": {
        "fractionalValue": "163/100",
        "expected": 38,
        "actual": 44,
        "id": 23226124
      },
      "away": {
        "fractionalValue": "1/2",
        "expected": 67,
        "actual": 71,
        "id": 23226125
      }
    }
  },
  {
    "source": "TennisApi",
    "odds_source": "TennisApi",
    "bookmaker": "TennisApi",
    "match_id": 16564859,
    "event_id": 16564859,
    "player1": "Anna Blinkova",
    "player2": "Sara Bejlek",
    "home_team": "Anna Blinkova",
    "away_team": "Sara Bejlek",
    "home_odds": 2.63,
    "away_odds": 1.5,
    "p1_odds": 2.63,
    "p2_odds": 1.5,
    "odds_player1": 2.63,
    "odds_player2": 1.5,
    "odds": 2.63,
    "odds1": 2.63,
    "odds2": 1.5,
    "price1": 2.63,
    "price2": 1.5,
    "raw": {
      "home": {
        "fractionalValue": "163/100",
        "expected": 38,
        "actual": 33,
        "id": 23202676
      },
      "away": {
        "fractionalValue": "1/2",
        "expected": 67,
        "actual": 55,
        "id": 23202677
      }
    }
  },
  {
    "source": "TennisApi",
    "odds_source": "TennisApi",
    "bookmaker": "TennisApi",
    "match_id": 16516196,
    "event_id": 16516196,
    "player1": "Dominika Salkova",
    "player2": "Oceane Dodin",
    "home_team": "Dominika Salkova",
    "away_team": "Oceane Dodin",
    "home_odds": 1.4,
    "away_odds": 3.0,
    "p1_odds": 1.4,
    "p2_odds": 3.0,
    "odds_player1": 1.4,
    "odds_player2": 3.0,
    "odds": 1.4,
    "odds1": 1.4,
    "odds2": 3.0,
    "price1": 1.4,
    "price2": 3.0,
    "raw": {
      "home": {
        "fractionalValue": "2/5",
        "expected": 71,
        "actual": 53,
        "id": 23263498
      },
      "away": {
        "fractionalValue": "2/1",
        "expected": 33,
        "actual": 38,
        "id": 23263499
      }
    }
  },
  {
    "source": "TennisApi",
    "odds_source": "TennisApi",
    "bookmaker": "TennisApi",
    "match_id": 16564901,
    "event_id": 16564901,
    "player1": "Lina Gjorcheska",
    "player2": "Erika Andreeva",
    "home_team": "Lina Gjorcheska",
    "away_team": "Erika Andreeva",
    "home_odds": 2.1,
    "away_odds": 1.6667,
    "p1_odds": 2.1,
    "p2_odds": 1.6667,
    "odds_player1": 2.1,
    "odds_player2": 1.6667,
    "odds": 2.1,
    "odds1": 2.1,
    "odds2": 1.6667,
    "price1": 2.1,
    "price2": 1.6667,
    "raw": {
      "home": {
        "fractionalValue": "11/10",
        "expected": 48,
        "actual": 23,
        "id": 23227567
      },
      "away": {
        "fractionalValue": "4/6",
        "expected": 60,
        "actual": 33,
        "id": 23227568
      }
    }
  },
  {
    "source": "TennisApi",
    "odds_source": "TennisApi",
    "bookmaker": "TennisApi",
    "match_id": 16564899,
    "event_id": 16564899,
    "player1": "Yasmine Kabbaj",
    "player2": "Deborah Chiesa",
    "home_team": "Yasmine Kabbaj",
    "away_team": "Deborah Chiesa",
    "home_odds": 4.0,
    "away_odds": 1.2222,
    "p1_odds": 4.0,
    "p2_odds": 1.2222,
    "odds_player1": 4.0,
    "odds_player2": 1.2222,
    "odds": 4.0,
    "odds1": 4.0,
    "odds2": 1.2222,
    "price1": 4.0,
    "price2": 1.2222,
    "raw": {
      "home": {
        "fractionalValue": "3/1",
        "expected": 25,
        "actual": 11,
        "id": 23227569
      },
      "away": {
        "fractionalValue": "2/9",
        "expected": 82,
        "actual": 91,
        "id": 23227570
      }
    }
  },
  {
    "source": "TennisApi",
    "odds_source": "TennisApi",
    "bookmaker": "TennisApi",
    "match_id": 16572707,
    "event_id": 16572707,
    "player1": "Amarissa Kiara Toth",
    "player2": "Jennifer Ruggeri",
    "home_team": "Amarissa Kiara Toth",
    "away_team": "Jennifer Ruggeri",
    "home_odds": 2.2,
    "away_odds": 1.6154,
    "p1_odds": 2.2,
    "p2_odds": 1.6154,
    "odds_player1": 2.2,
    "odds_player2": 1.6154,
    "odds": 2.2,
    "odds1": 2.2,
    "odds2": 1.6154,
    "price1": 2.2,
    "price2": 1.6154,
    "raw": {
      "home": {
        "fractionalValue": "6/5",
        "expected": 45,
        "actual": 42,
        "id": 23240307
      },
      "away": {
        "fractionalValue": "8/13",
        "expected": 62,
        "actual": 59,
        "id": 23240308
      }
    }
  },
  {
    "source": "TennisApi",
    "odds_source": "TennisApi",
    "bookmaker": "TennisApi",
    "match_id": 16564902,
    "event_id": 16564902,
    "player1": "Federica Urgesi",
    "player2": "Elizara Yaneva",
    "home_team": "Federica Urgesi",
    "away_team": "Elizara Yaneva",
    "home_odds": 3.0,
    "away_odds": 1.3636,
    "p1_odds": 3.0,
    "p2_odds": 1.3636,
    "odds_player1": 3.0,
    "odds_player2": 1.3636,
    "odds": 3.0,
    "odds1": 3.0,
    "odds2": 1.3636,
    "price1": 3.0,
    "price2": 1.3636,
    "raw": {
      "home": {
        "fractionalValue": "2/1",
        "expected": 33,
        "actual": 32,
        "id": 23228065
      },
      "away": {
        "fractionalValue": "4/11",
        "expected": 74,
        "actual": 75,
        "id": 23228066
      }
    }
  },
  {
    "source": "TennisApi",
    "odds_source": "TennisApi",
    "bookmaker": "TennisApi",
    "match_id": 16564898,
    "event_id": 16564898,
    "player1": "Alessandra Mazzola",
    "player2": "Dalila Spiteri",
    "home_team": "Alessandra Mazzola",
    "away_team": "Dalila Spiteri",
    "home_odds": 1.4444,
    "away_odds": 2.625,
    "p1_odds": 1.4444,
    "p2_odds": 2.625,
    "odds_player1": 1.4444,
    "odds_player2": 2.625,
    "odds": 1.4444,
    "odds1": 1.4444,
    "odds2": 2.625,
    "price1": 1.4444,
    "price2": 2.625,
    "raw": {
      "home": {
        "fractionalValue": "4/9",
        "expected": 69,
        "actual": 70,
        "id": 23240815
      },
      "away": {
        "fractionalValue": "13/8",
        "expected": 38,
        "actual": 11,
        "id": 23240816
      }
    }
  },
  {
    "source": "TennisApi",
    "odds_source": "TennisApi",
    "bookmaker": "TennisApi",
    "match_id": 16572715,
    "event_id": 16572715,
    "player1": "Caroline Werner",
    "player2": "Mina Hodzic",
    "home_team": "Caroline Werner",
    "away_team": "Mina Hodzic",
    "home_odds": 1.5,
    "away_odds": 2.5,
    "p1_odds": 1.5,
    "p2_odds": 2.5,
    "odds_player1": 1.5,
    "odds_player2": 2.5,
    "odds": 1.5,
    "odds1": 1.5,
    "odds2": 2.5,
    "price1": 1.5,
    "price2": 2.5,
    "raw": {
      "home": {
        "fractionalValue": "1/2",
        "expected": 67,
        "actual": 67,
        "id": 23258797
      },
      "away": {
        "fractionalValue": "6/4",
        "expected": 40,
        "actual": 27,
        "id": 23258798
      }
    }
  },
  {
    "source": "TennisApi",
    "odds_source": "TennisApi",
    "bookmaker": "TennisApi",
    "match_id": 16572714,
    "event_id": 16572714,
    "player1": "Noemi Basiletti",
    "player2": "Tyra Caterina Grant",
    "home_team": "Noemi Basiletti",
    "away_team": "Tyra Caterina Grant",
    "home_odds": 3.25,
    "away_odds": 1.3333,
    "p1_odds": 3.25,
    "p2_odds": 1.3333,
    "odds_player1": 3.25,
    "odds_player2": 1.3333,
    "odds": 3.25,
    "odds1": 3.25,
    "odds2": 1.3333,
    "price1": 3.25,
    "price2": 1.3333,
    "raw": {
      "home": {
        "fractionalValue": "9/4",
        "expected": 31,
        "actual": 43,
        "id": 23258795
      },
      "away": {
        "fractionalValue": "1/3",
        "expected": 75,
        "actual": 77,
        "id": 23258796
      }
    }
  },
  {
    "source": "TennisApi",
    "odds_source": "TennisApi",
    "bookmaker": "TennisApi",
    "match_id": 16564904,
    "event_id": 16564904,
    "player1": "Alice Rame",
    "player2": "Anastasia Tikhonova",
    "home_team": "Alice Rame",
    "away_team": "Anastasia Tikhonova",
    "home_odds": 1.6154,
    "away_odds": 2.2,
    "p1_odds": 1.6154,
    "p2_odds": 2.2,
    "odds_player1": 1.6154,
    "odds_player2": 2.2,
    "odds": 1.6154,
    "odds1": 1.6154,
    "odds2": 2.2,
    "price1": 1.6154,
    "price2": 2.2,
    "raw": {
      "home": {
        "fractionalValue": "8/13",
        "expected": 62,
        "actual": 38,
        "id": 23258983
      },
      "away": {
        "fractionalValue": "6/5",
        "expected": 45,
        "actual": 26,
        "id": 23258984
      }
    }
  },
  {
    "source": "TennisApi",
    "odds_source": "TennisApi",
    "bookmaker": "TennisApi",
    "match_id": 16564905,
    "event_id": 16564905,
    "player1": "Tamara Zidanšek",
    "player2": "Alevtina Ibragimova",
    "home_team": "Tamara Zidanšek",
    "away_team": "Alevtina Ibragimova",
    "home_odds": 1.5,
    "away_odds": 2.5,
    "p1_odds": 1.5,
    "p2_odds": 2.5,
    "odds_player1": 1.5,
    "odds_player2": 2.5,
    "odds": 1.5,
    "odds1": 1.5,
    "odds2": 2.5,
    "price1": 1.5,
    "price2": 2.5,
    "raw": {
      "home": {
        "fractionalValue": "1/2",
        "expected": 67,
        "actual": 58,
        "id": 23258515
      },
      "away": {
        "fractionalValue": "6/4",
        "expected": 40,
        "actual": 9,
        "id": 23258516
      }
    }
  },
  {
    "source": "TennisApi",
    "odds_source": "TennisApi",
    "bookmaker": "TennisApi",
    "match_id": 16564907,
    "event_id": 16564907,
    "player1": "Miriam Bulgaru",
    "player2": "Caijsa Wilda Hennemann",
    "home_team": "Miriam Bulgaru",
    "away_team": "Caijsa Wilda Hennemann",
    "home_odds": 2.75,
    "away_odds": 1.4,
    "p1_odds": 2.75,
    "p2_odds": 1.4,
    "odds_player1": 2.75,
    "odds_player2": 1.4,
    "odds": 2.75,
    "odds1": 2.75,
    "odds2": 1.4,
    "price1": 2.75,
    "price2": 1.4,
    "raw": {
      "home": {
        "fractionalValue": "7/4",
        "expected": 36,
        "actual": 22,
        "id": 23258981
      },
      "away": {
        "fractionalValue": "2/5",
        "expected": 71,
        "actual": 88,
        "id": 23258982
      }
    }
  }
]