{
  "saved_at": 1783659064.1246235,
  "data": {
    "event": {
      "tournament": {
        "name": "ITF W15 Astana Women",
        "slug": "itf-w15-astana-women",
        "category": {
          "name": "ITF Women",
          "slug": "itf-women",
          "sport": {
            "name": "Tennis",
            "slug": "tennis",
            "id": 5
          },
          "priority": 3,
          "country": {},
          "id": 213,
          "flag": "itf-women",
          "fieldTranslations": {
            "nameTranslation": {
              "ar": "اتحاد التنس الدولي للسيدات",
              "ru": "Женский мировой теннисный тур ITF"
            },
            "shortNameTranslation": {}
          }
        },
        "uniqueTournament": {
          "name": "ITF W15 Astana Women",
          "slug": "itf-w15-astana-women",
          "category": {
            "name": "ITF Women",
            "slug": "itf-women",
            "sport": {
              "name": "Tennis",
              "slug": "tennis",
              "id": 5
            },
            "priority": 3,
            "country": {},
            "id": 213,
            "flag": "itf-women",
            "fieldTranslations": {
              "nameTranslation": {
                "ar": "اتحاد التنس الدولي للسيدات",
                "ru": "Женский мировой теннисный тур ITF"
              },
              "shortNameTranslation": {}
            }
          },
          "userCount": 21,
          "groundType": "Hardcourt outdoor",
          "hasRounds": true,
          "hasPerformanceGraphFeature": false,
          "country": {},
          "id": 28461,
          "hasEventPlayerStatistics": false,
          "displayInverseHomeAwayTeams": false,
          "fieldTranslations": {
            "nameTranslation": {
              "ar": "ITF W15 أستانا للسيدات",
              "ru": "Астана, женщины"
            },
            "shortNameTranslation": {}
          }
        },
        "priority": 0,
        "competitionType": 2,
        "id": 159864,
        "fieldTranslations": {
          "nameTranslation": {
            "ar": "بطولة السيدات (ITF) W15 أستانا",
            "ru": "ITF W15, Астана, женщины"
          },
          "shortNameTranslation": {}
        }
      },
      "season": {
        "name": "2026 ",
        "year": "2026",
        "editor": false,
        "id": 97578
      },
      "roundInfo": {
        "round": 27,
        "name": "Quarterfinals",
        "slug": "quarterfinals",
        "cupRoundType": 4
      },
      "customId": "WAAcsXvNi",
      "status": {
        "code": 0,
        "description": "Not started",
        "type": "notstarted"
      },
      "homeTeam": {
        "name": "Ekaterina Tupitsyna",
        "slug": "tupitsyna-ekaterina",
        "shortName": "E. Tupitsyna",
        "gender": "F",
        "sport": {
          "name": "Tennis",
          "slug": "tennis",
          "id": 5
        },
        "userCount": 185,
        "playerTeamInfo": {
          "prizeCurrent": 6715,
          "prizeTotal": 9178,
          "id": 21856,
          "underage": false,
          "prizeCurrentRaw": {
            "value": 6715,
            "currency": "EUR"
          },
          "prizeTotalRaw": {
            "value": 9178,
            "currency": "EUR"
          },
          "currentRanking": 697
        },
        "nameCode": "TUP",
        "ranking": 708,
        "disabled": false,
        "national": false,
        "type": 1,
        "country": {
          "alpha2": "RU",
          "alpha3": "RUS",
          "name": "Russia",
          "slug": "russia"
        },
        "id": 1096047,
        "fullName": "Ekaterina Tupitsyna",
        "subTeams": [],
        "teamColors": {
          "primary": "#374df5",
          "secondary": "#374df5",
          "text": "#ffffff"
        },
        "fieldTranslations": {
          "nameTranslation": {
            "ar": "يكاتيرينا توبيتسينا",
            "ru": "Екатерина Тупицына"
          },
          "shortNameTranslation": {
            "ar": "ي. توبيتسينا",
            "ru": "Е. Тупицына"
          }
        },
        "timeActive": []
      },
      "awayTeam": {
        "name": "Ekaterina Maklakova",
        "slug": "maklakova-ekaterina",
        "shortName": "E. Maklakova",
        "gender": "F",
        "sport": {
          "name": "Tennis",
          "slug": "tennis",
          "id": 5
        },
        "userCount": 309,
        "playerTeamInfo": {
          "prizeCurrent": 11441,
          "prizeTotal": 71966,
          "id": 4804,
          "underage": false,
          "prizeCurrentRaw": {
            "value": 11441,
            "currency": "EUR"
          },
          "prizeTotalRaw": {
            "value": 71966,
            "currency": "EUR"
          },
          "currentRanking": 487
        },
        "nameCode": "MAK",
        "ranking": 488,
        "national": false,
        "type": 1,
        "country": {
          "alpha2": "RU",
          "alpha3": "RUS",
          "name": "Russia",
          "slug": "russia"
        },
        "id": 313796,
        "fullName": "Ekaterina Maklakova",
        "subTeams": [],
        "teamColors": {
          "primary": "#374df5",
          "secondary": "#374df5",
          "text": "#ffffff"
        },
        "fieldTranslations": {
          "nameTranslation": {
            "ar": "يكاتيرينا ماكلوكوفا",
            "ru": "Екатерина Маклакова"
          },
          "shortNameTranslation": {
            "ar": "ي. ماكلوكوفا",
            "ru": "Е. Маклакова"
          }
        },
        "timeActive": []
      },
      "homeScore": {},
      "awayScore": {},
      "time": {},
      "changes": {
        "changeTimestamp": 0
      },
      "hasGlobalHighlights": false,
      "crowdsourcingDataDisplayEnabled": false,
      "id": 16477359,
      "defaultPeriodCount": 3,
      "slug": "ekaterina-tupitsyna-ekaterina-maklakova",
      "startTimestamp": 1783659600,
      "periods": {
        "point": "Game",
        "current": "Match",
        "period1": "1st set",
        "period2": "2nd set",
        "period3": "3rd set",
        "period4": "4th set",
        "period5": "5th set"
      },
      "finalResultOnly": false,
      "feedLocked": false,
      "groundType": "Hardcourt outdoor",
      "showTotoPromo": true,
      "isEditor": false,
      "eventFilters": {
        "category": [
          "singles"
        ],
        "level": [
          "pro"
        ],
        "tournament": [
          "lower"
        ],
        "gender": [
          "F"
        ]
      }
    }
  }
}